[
  {
    "link": "https://bid.cars/ru/lot/1-92102545/2024-Volkswagen-Atlas-1V2HR2CA3RC535536",
    "title": "2024 Volkswagen Atlas, SE",
    "vin": "1V2HR2CA3RC535536",
    "lot": "1-92102545",
    "odometer": "34k мили (55k km)",
    "damage": "Передняя часть",
    "location": "Jackson (MS)",
    "currentBid": "$0",
    "engine": "2.0L 4 cyl. 269HP",
    "keys": "ST (Mississippi)",
    "condition": "На ходу",
    "auctionDate": "пт 10 апр., 19:00 GMT+2",
    "auctionSource": "Copart",
    "seller": "---"
  }
]