[
  {
    "link": "https://bid.cars/ru/lot/1-75992885/2024-Volkswagen-Atlas-1V2BR2CA3RC514286",
    "title": "2024 Volkswagen Atlas, Sel",
    "vin": "1V2BR2CA3RC514286",
    "lot": "1-75992885",
    "odometer": "22k мили (35k km)",
    "damage": "Задняя часть",
    "location": "Minneapolis (MN)",
    "currentBid": "$3,600",
    "engine": "2.0L 4 cyl. 269HP",
    "keys": "ST (Minnesota)",
    "condition": "На ходу",
    "auctionDate": "вт 14 апр., 19:00 GMT+2",
    "auctionSource": "Copart",
    "seller": "Geico"
  },
  {
    "link": "https://bid.cars/ru/lot/1-49740786/2024-Volkswagen-Atlas-1V2HR2CA9RC557475",
    "title": "2024 Volkswagen Atlas, SE",
    "vin": "1V2HR2CA9RC557475",
    "lot": "1-49740786",
    "odometer": "54k мили (88k km)",
    "damage": "Передняя часть",
    "location": "Cleveland... (OH)",
    "currentBid": "$90",
    "engine": "2.0L 4 cyl. 269HP",
    "keys": "CT (Ohio)",
    "condition": "На ходу",
    "auctionDate": "ср 15 апр., 18:00 GMT+2",
    "auctionSource": "Copart",
    "seller": "Enterprise"
  },
  {
    "link": "https://bid.cars/ru/lot/1-46406336/2026-Volkswagen-Atlas-1V2HN2CAXTC513472",
    "title": "2026 Volkswagen Atlas, SE",
    "vin": "1V2HN2CAXTC513472",
    "lot": "1-46406336",
    "odometer": "7k мили (11k km)",
    "damage": "Задняя часть",
    "location": "Wichita (KS)",
    "currentBid": "$225",
    "engine": "2.0L 4 cyl. 269HP",
    "keys": "CT (Oklahoma)",
    "condition": "На ходу",
    "auctionDate": "ср 15 апр., 18:00 GMT+2",
    "auctionSource": "Copart",
    "seller": "Hertz"
  },
  {
    "link": "https://bid.cars/ru/lot/1-49070856/2025-Volkswagen-Atlas-1V2WE2CA7SC220571",
    "title": "2025 Volkswagen Atlas, Sel Premium R...",
    "vin": "1V2WE2CA7SC220571",
    "lot": "1-49070856",
    "odometer": "22k мили (36k km)",
    "damage": "Передняя часть",
    "location": "Chicago South (IL)",
    "currentBid": "$0",
    "engine": "2.0L 4 cyl. 269HP",
    "keys": "SC (Tennessee)",
    "condition": "На ходу",
    "auctionDate": "ср 15 апр., 19:00 GMT+2",
    "auctionSource": "Copart",
    "seller": "---"
  },
  {
    "link": "https://bid.cars/ru/lot/1-45517816/2024-Volkswagen-Atlas-1V2JR2CA0RC522180",
    "title": "2024 Volkswagen Atlas, SE",
    "vin": "1V2JR2CA0RC522180",
    "lot": "1-45517816",
    "odometer": "29k мили (46k km)",
    "damage": "Задняя часть",
    "location": "Cartersville (GA)",
    "currentBid": "$250",
    "engine": "2.0L 4 cyl. 269HP",
    "keys": "ST (Georgia)",
    "condition": "На ходу",
    "auctionDate": "чт 16 апр., 16:00 GMT+2",
    "auctionSource": "Copart",
    "seller": "Geico"
  },
  {
    "link": "https://bid.cars/ru/lot/1-79745175/2024-Volkswagen-Atlas-1V2WE2CA3RC259748",
    "title": "2024 Volkswagen Atlas, SE",
    "vin": "1V2WE2CA3RC259748",
    "lot": "1-79745175",
    "odometer": "17k мили (28k km)",
    "damage": "Передняя часть",
    "location": "Corpus Chr... (TX)",
    "currentBid": "$0",
    "engine": "2.0L 4 cyl. 269HP",
    "keys": "SV (Texas)",
    "condition": "На ходу",
    "auctionDate": "вт 21 апр., 19:00 GMT+2",
    "auctionSource": "Copart",
    "seller": "---"
  }
]